mcp_kql_server/__init__.py
mcp_kql_server/__main__.py
mcp_kql_server/ai_prompts.py
mcp_kql_server/constants.py
mcp_kql_server/execute_kql.py
mcp_kql_server/kql_auth.py
mcp_kql_server/kql_validator.py
mcp_kql_server/mcp_server.py
mcp_kql_server/memory.py
mcp_kql_server/performance.py
mcp_kql_server/py.typed
mcp_kql_server/utils.py
mcp_kql_server/version_checker.py
mcp_kql_server-2.1.0.dist-info/METADATA
mcp_kql_server-2.1.0.dist-info/WHEEL
mcp_kql_server-2.1.0.dist-info/entry_points.txt
mcp_kql_server-2.1.0.dist-info/licenses/LICENSE
mcp_kql_server-2.1.0.dist-info/RECORD
