Metadata-Version: 2.4
Name: mcp-kql-server
Version: 2.1.0
Summary: AI-Powered MCP server for KQL query execution with Natural Language to KQL (NL2KQL) conversion, intelligent schema memory, RAG-enhanced context assistance, and semantic search capabilities
Project-URL: Homepage, https://github.com/4R9UN/mcp-kql-server
Project-URL: Repository, https://github.com/4R9UN/mcp-kql-server.git
Project-URL: Issues, https://github.com/4R9UN/mcp-kql-server/issues
Project-URL: Changelog, https://github.com/4R9UN/mcp-kql-server/blob/main/CHANGELOG.md
Author-email: Arjun Trivedi <arjuntrivedi42@yahoo.com>
License: MIT
License-File: LICENSE
Keywords: ai,authentication,azure,azure-data-explorer,data-analytics,generative-ai,intelligent-caching,kql,kql-server,kusto,large-language-model,llm,machine-learning,mcp,mcp-server,mcp-tool,model-context-protocol,query-execution,rag,retrieval-augmented-generation,schema-management,schema-memory,semantic-search,sentence-transformers,vector-search
Classifier: Development Status :: 5 - Production/Stable
Classifier: Intended Audience :: Developers
Classifier: Intended Audience :: System Administrators
Classifier: License :: OSI Approved :: MIT License
Classifier: Operating System :: OS Independent
Classifier: Programming Language :: Python :: 3
Classifier: Programming Language :: Python :: 3.10
Classifier: Programming Language :: Python :: 3.11
Classifier: Programming Language :: Python :: 3.12
Classifier: Topic :: Database
Classifier: Topic :: Database :: Database Engines/Servers
Classifier: Topic :: Scientific/Engineering :: Artificial Intelligence
Classifier: Topic :: Scientific/Engineering :: Information Analysis
Classifier: Topic :: Software Development :: Libraries :: Python Modules
Requires-Python: >=3.10
Requires-Dist: azure-cli
Requires-Dist: azure-identity<2.0.0,>=1.15.0
Requires-Dist: azure-kusto-data<6.0.0,>=4.0.0
Requires-Dist: click<9.0.0,>=8.0.0
Requires-Dist: colorama<1.0.0,>=0.4.6
Requires-Dist: fastmcp<3.0.0,>=2.0.0
Requires-Dist: httpx<1.0.0,>=0.25.0
Requires-Dist: numpy<3.0.0,>=1.21.0
Requires-Dist: pandas
Requires-Dist: pydantic<3.0.0,>=2.0.0
Requires-Dist: pytest
Requires-Dist: python-dotenv<2.0.0,>=1.0.0
Requires-Dist: requests<3.0.0,>=2.31.0
Requires-Dist: scikit-learn<2.0.0,>=1.0.0
Requires-Dist: sentence-transformers<6.0.0,>=2.0.0
Requires-Dist: tabulate<1.0.0,>=0.9.0
Requires-Dist: tenacity<10.0.0,>=8.0.0
Requires-Dist: typing-extensions<5.0.0,>=4.0.0
